preling/__init__.py
preling/preling.py
preling/app/__init__.py
preling/app/app.py
preling/app/commands/__init__.py
preling/app/commands/delete.py
preling/app/commands/init.py
preling/app/commands/path.py
preling/app/commands/stats.py
preling/app/commands/study/__init__.py
preling/app/commands/study/chooser.py
preling/app/commands/study/evaluator.py
preling/app/commands/study/explainer.py
preling/app/commands/study/interaction.py
preling/app/commands/study/tts.py
preling/app/commands/study/updater.py
preling/db/__init__.py
preling/db/base.py
preling/db/models.py
preling/utils/__init__.py
preling/utils/console.py
preling/utils/paths.py
preling/utils/strings.py
preling/utils/time.py
preling/utils/typer.py
preling-1.3.1.dist-info/licenses/LICENSE
preling-1.3.1.dist-info/METADATA
preling-1.3.1.dist-info/WHEEL
preling-1.3.1.dist-info/entry_points.txt
preling-1.3.1.dist-info/top_level.txt
preling-1.3.1.dist-info/RECORD
