Metadata-Version: 2.4
Name: preling
Version: 1.3.1
Summary: Command-line tool for learning foreign languages through gradual exposure to new vocabulary
Home-page: https://github.com/danmysak/preling
Author: Danylo Mysak
Author-email: danmysak@gmail.com
Project-URL: Bug Tracker, https://github.com/danmysak/preling/issues
Classifier: Programming Language :: Python :: 3
Classifier: License :: OSI Approved :: MIT License
Classifier: Operating System :: OS Independent
Requires-Python: >=3.12
License-File: LICENSE
Requires-Dist: openai[voice_helpers]
Requires-Dist: prompt_toolkit
Requires-Dist: pyaudio
Requires-Dist: spacy
Requires-Dist: SQLAlchemy
Requires-Dist: tqdm
Requires-Dist: typer
Provides-Extra: ja
Requires-Dist: spacy[ja]; extra == "ja"
Dynamic: license-file
